PyCrowdTangle/PyCrowdTangle.py
PyCrowdTangle/__init__.py
tests/__init__.py
tests/test_PyCrwodTangle.py
PyCrowdTangle-0.5.0.dist-info/LICENSE
PyCrowdTangle-0.5.0.dist-info/METADATA
PyCrowdTangle-0.5.0.dist-info/WHEEL
PyCrowdTangle-0.5.0.dist-info/top_level.txt
PyCrowdTangle-0.5.0.dist-info/RECORD
