Metadata-Version: 2.1
Name: PyCrowdTangle
Version: 0.5.0
Summary: A Python Wrapper To Retrieve Data From The CrowdTangle API
Home-page: https://github.com/UPB-SS1/PyCrowdTangle
Author: Jose R. Zapata
Author-email: jjrzg@hotmail.com
License: MIT
Keywords: crowdtangle,wrapper-api
Platform: UNKNOWN
Classifier: Programming Language :: Python :: 3.7
Classifier: License :: OSI Approved :: MIT License
Requires-Dist: requests
